amqp_client_python/__init__.py
amqp_client_python/domain/models/__init__.py
amqp_client_python/domain/models/config.py
amqp_client_python/domain/models/options.py
amqp_client_python/domain/models/ssl_options.py
amqp_client_python/domain/utils/__init__.py
amqp_client_python/domain/utils/connection_type.py
amqp_client_python/domain/utils/types.py
amqp_client_python/event/__init__.py
amqp_client_python/event/async_provider_handler.py
amqp_client_python/event/async_subscriber_handler.py
amqp_client_python/event/event.py
amqp_client_python/event/integration_event.py
amqp_client_python/event/integration_event_handler.py
amqp_client_python/event/provider_handler.py
amqp_client_python/event/subscriber_handler.py
amqp_client_python/exceptions/__init__.py
amqp_client_python/exceptions/auto_reconnect_exception.py
amqp_client_python/exceptions/blocking_exception.py
amqp_client_python/exceptions/eventbus_exception.py
amqp_client_python/exceptions/nack_exception.py
amqp_client_python/exceptions/publish_timeout_exception.py
amqp_client_python/exceptions/response_timeout_exception.py
amqp_client_python/exceptions/rpc_provider_exception.py
amqp_client_python/exceptions/thread_unsafe_exception.py
amqp_client_python/exceptions/timeout_exception.py
amqp_client_python/py.typed
amqp_client_python/rabbitmq/__init__.py
amqp_client_python/rabbitmq/async_channel.py
amqp_client_python/rabbitmq/async_channel_factory.py
amqp_client_python/rabbitmq/async_connection.py
amqp_client_python/rabbitmq/async_connection_factory.py
amqp_client_python/rabbitmq/async_eventbus_rabbitmq.py
amqp_client_python/rabbitmq/channel_factory_rabbitmq.py
amqp_client_python/rabbitmq/channel_rabbitmq.py
amqp_client_python/rabbitmq/connection_factory_rabbitmq.py
amqp_client_python/rabbitmq/connection_rabbitmq.py
amqp_client_python/rabbitmq/eventbus_rabbitmq.py
amqp_client_python/rabbitmq/eventbus_wrapper_rabbitmq.py
amqp_client_python/rabbitmq/ioloop_factory.py
amqp_client_python/signals.py
amqp_client_python-0.2.0.dist-info/LICENSE
amqp_client_python-0.2.0.dist-info/METADATA
amqp_client_python-0.2.0.dist-info/WHEEL
amqp_client_python-0.2.0.dist-info/RECORD
