Metadata-Version: 2.1
Name: amqp-client-python
Version: 0.2.0
Summary: Python AMQP Client Library
Home-page: https://github.com/nutes-uepb/amqp-client-python
License: Apache-2.0
Keywords: packaging,dependency,amqp-client-python
Author: NUTES UEPB
Author-email: dev.seniorsaudemovel@gmail.com
Requires-Python: >=3.7,<4.0
Classifier: Development Status :: 5 - Production/Stable
Classifier: Intended Audience :: Developers
Classifier: License :: OSI Approved :: Apache Software License
Classifier: Natural Language :: English
Classifier: Operating System :: OS Independent
Classifier: Programming Language :: Python :: 3
Classifier: Programming Language :: Python :: 3.7
Classifier: Programming Language :: Python :: 3.8
Classifier: Programming Language :: Python :: 3.9
Classifier: Programming Language :: Python :: 3.10
Classifier: Programming Language :: Python :: 3.11
Classifier: Programming Language :: Python :: 3.12
Classifier: Topic :: Communications
Classifier: Topic :: Internet
Classifier: Topic :: Software Development :: Libraries
Classifier: Topic :: Software Development :: Libraries :: Python Modules
Classifier: Topic :: System :: Networking
Requires-Dist: pika (>=1.3.0,<2.0.0)
Project-URL: Bug Tracker, https://github.com/nutes-uepb/amqp-client-python/issues
Project-URL: Repository, https://github.com/nutes-uepb/amqp-client-python
